README.md
setup.py
aworker/__init__.py
aworker/exceptions.py
aworker/processor.py
aworker/serializers.py
aworker/task.py
aworker.egg-info/PKG-INFO
aworker.egg-info/SOURCES.txt
aworker.egg-info/dependency_links.txt
aworker.egg-info/top_level.txt
aworker/queue/__init__.py
aworker/queue/base.py
aworker/queue/memory.py
aworker/tests/__init__.py
aworker/tests/test_serializer.py
aworker/tests/test_task.py
aworker/tests/test_task_processor.py
aworker/tests/test_worker.py